{
	"instanceIdA": {
		"dbConnection":"value",
		"cacheKey":"value",
		"poolId":"default_10721789",
		"farmId":"default_10721789"
	},
	"instanceIdB": {
		"dbConnection":"value",
		"cacheKey":"value",
		"poolId":"default_10721789",
		"farmId":"default_10721789"
	},
	"instanceIdC": {
		"dbConnection":"value",
		"cacheKey":"value",
		"poolId":"default_10732789",
		"farmId":"default_10732789"
	},
	"instanceIdD": {
		"dbConnection":"value",
		"cacheKey":"value",
		"poolId":"default_10732789",
		"farmId":"default_10732789"
	},
	"instanceIdE": {
		"dbConnection":"value",
		"cacheKey":"value",
		"poolId":"default_10732789",
		"farmId":"instanceE_10732789"
	},
	"instanceIdX": {
		"dbConnection":"value",
		"cacheKey":"value",
		"poolId":"default_10743289",
		"farmId":"default_10743289"
	},
	"instanceIdY": {
		"dbConnection":"value",
		"cacheKey":"value",
		"poolId":"default_10743289",
		"farmId":"default_10743289"
	},
	"instanceIdZ": {
		"dbConnection":"value",
		"cacheKey":"value",
		"poolId":"default_10743289",
		"farmId":"default_10743289"
	}	
}